lhpcdt/__init__.py
lhpcdt/basic_config.py
lhpcdt/conda_utils.py
lhpcdt/config.py
lhpcdt/config_template.py
lhpcdt/desktop.py
lhpcdt/gfxconfig.py
lhpcdt/gfxlaunch.py
lhpcdt/gfxmenu.py
lhpcdt/gfxnodes.py
lhpcdt/gfxusage.py
lhpcdt/hostlist.py
lhpcdt/integration.py
lhpcdt/intrun.py
lhpcdt/job_ui.py
lhpcdt/jobs.py
lhpcdt/launcher.py
lhpcdt/lmod.py
lhpcdt/lmod_ui.py
lhpcdt/lrms.py
lhpcdt/modules.json
lhpcdt/monitor.py
lhpcdt/node_monitor.py
lhpcdt/remote.py
lhpcdt/resource_win.py
lhpcdt/resources.py
lhpcdt/scripts.py
lhpcdt/settings.py
lhpcdt/setup_win.py
lhpcdt/singleton.py
lhpcdt/slpp.py
lhpcdt/slurm.py
lhpcdt/splash_win.py
lhpcdt/toolbar_icons_rc.py
lhpcdt/ui_job_info.py
lhpcdt/ui_lmod_query.py
lhpcdt/ui_main_window_simplified.py
lhpcdt/ui_node_window.py
lhpcdt/ui_notebook_job_prop_win.py
lhpcdt/ui_resource_specification.py
lhpcdt/ui_session_manager.py
lhpcdt/ui_setup_window.py
lhpcdt/user_config.py
lhpcdt/xmltodict.py
gfxlauncher-0.9.19.dist-info/entry_points.txt
gfxlauncher-0.9.19.dist-info/WHEEL
gfxlauncher-0.9.19.dist-info/METADATA
gfxlauncher-0.9.19.dist-info/licenses/LICENSE
gfxlauncher-0.9.19.dist-info/RECORD
