Metadata-Version: 2.1
Name: gfxlauncher
Version: 0.9.19
Summary: The GFX Launcher toolkit provide the means for launching graphical applications through SLURM. The toolkit comes with a configurable launcher, graphical job monitor and tools for automatically generating menus and shortcuts for the launcher.
License: GPL-3.0
Author-email: Jonas Lindemann <jonas.lindemann@lunarc.lu.se>
Requires-Python: >=3.6
Requires-Dist: pyqt5>=5.15.6
Requires-Dist: qtpy>=2.0.1
